chemcoord/__init__.py
chemcoord/configuration.py
chemcoord/constants.py
chemcoord/exceptions.py
chemcoord/_generic_classes/__init__.py
chemcoord/_generic_classes/generic_IO.py
chemcoord/_generic_classes/generic_core.py
chemcoord/cartesian_coordinates/__init__.py
chemcoord/cartesian_coordinates/_cart_transformation.py
chemcoord/cartesian_coordinates/_cartesian_class_core.py
chemcoord/cartesian_coordinates/_cartesian_class_get_zmat.py
chemcoord/cartesian_coordinates/_cartesian_class_io.py
chemcoord/cartesian_coordinates/_cartesian_class_pandas_wrapper.py
chemcoord/cartesian_coordinates/_cartesian_class_symmetry.py
chemcoord/cartesian_coordinates/_indexers.py
chemcoord/cartesian_coordinates/asymmetric_unit_cartesian_class.py
chemcoord/cartesian_coordinates/cartesian_class_main.py
chemcoord/cartesian_coordinates/point_group.py
chemcoord/cartesian_coordinates/xyz_functions.py
chemcoord/internal_coordinates/__init__.py
chemcoord/internal_coordinates/_indexers.py
chemcoord/internal_coordinates/_zmat_class_core.py
chemcoord/internal_coordinates/_zmat_class_io.py
chemcoord/internal_coordinates/_zmat_class_pandas_wrapper.py
chemcoord/internal_coordinates/_zmat_transformation.py
chemcoord/internal_coordinates/zmat_class_main.py
chemcoord/internal_coordinates/zmat_functions.py
chemcoord/utilities/__init__.py
chemcoord/utilities/_decorators.py
chemcoord/utilities/_print_versions.py
chemcoord/utilities/_temporary_deprecation_workarounds.py
chemcoord-2.1.2.dist-info/LICENSE.md
chemcoord-2.1.2.dist-info/METADATA
chemcoord-2.1.2.dist-info/WHEEL
chemcoord-2.1.2.dist-info/top_level.txt
chemcoord-2.1.2.dist-info/RECORD
