Metadata-Version: 2.1
Name: chemcoord
Version: 2.1.2
Summary: Python module for dealing with chemical coordinates.
Home-page: https://github.com/mcocdawc/chemcoord
Author: Oskar Weser
Author-email: oskar.weser@gmail.com
License: LGPLv3
Keywords: chemcoord,transformation,cartesian,internal,chemistry,zmatrix,xyz,zmat,coordinates,coordinate system
Classifier: Development Status :: 5 - Production/Stable
Classifier: Environment :: Console
Classifier: Intended Audience :: Science/Research
Classifier: License :: OSI Approved :: GNU Lesser General Public License v3 (LGPLv3)
Classifier: Operating System :: Unix
Classifier: Operating System :: POSIX
Classifier: Operating System :: Microsoft :: Windows
Classifier: Natural Language :: English
Classifier: Programming Language :: Python
Classifier: Programming Language :: Python :: 3.7
Classifier: Programming Language :: Python :: 3.8
Classifier: Programming Language :: Python :: 3.9
Classifier: Programming Language :: Python :: 3.10
Classifier: Programming Language :: Python :: 3.11
Classifier: Topic :: Scientific/Engineering :: Chemistry
Classifier: Topic :: Scientific/Engineering :: Physics
License-File: LICENSE.md
Requires-Dist: numpy >=1.0
Requires-Dist: pandas >=1.0
Requires-Dist: numba >=0.35
Requires-Dist: sortedcontainers
Requires-Dist: sympy
Requires-Dist: six
Requires-Dist: pymatgen
